nf6x_eetools/__init__.py
nf6x_eetools/drilltables.py
nf6x_eetools/engformatter.py
nf6x_eetools/eseries.py
nf6x_eetools/fractional.py
nf6x_eetools-1.0.1.dist-info/LICENSE
nf6x_eetools-1.0.1.dist-info/WHEEL
nf6x_eetools-1.0.1.dist-info/METADATA
nf6x_eetools-1.0.1.dist-info/RECORD
