Metadata-Version: 2.1
Name: nf6x_eetools
Version: 1.0.1
Summary: NF6X's misc. electrical engineering related tools.
Keywords: drill,EE,fractional,IEC 60063:2015,resistor
Author-email: "Mark J. Blair" <nf6x@nf6x.net>
Requires-Python: >3.8
Classifier: Development Status :: 4 - Beta
Classifier: Programming Language :: Python
Classifier: Programming Language :: Python :: 3
Classifier: Programming Language :: Python :: 3.8
Classifier: Programming Language :: Python :: 3.9
Classifier: License :: OSI Approved :: GNU General Public License v3 (GPLv3)
Classifier: Operating System :: OS Independent
Project-URL: Source, https://gitlab.com/NF6X_Development/nf6x_eetools
